remote/__init__.py
remote/handlers/__init__.py
remote/handlers/core_handler.py
remote/handlers/metadata.py
remote/moudels/__init__.py
remote/moudels/account/__init__.py
remote/moudels/account/account_manager.py
remote/moudels/account/account_viewer.py
remote/moudels/account/cleaner.py
remote/moudels/account/client/__init__.py
remote/moudels/account/client/client_manager.py
remote/moudels/account/device/__init__.py
remote/moudels/account/device/device_manager.py
remote/moudels/account/profile/__init__.py
remote/moudels/account/profile/profile_info.py
remote/moudels/account/profile/profile_media.py
remote/moudels/account/profile/profile_privacy.py
remote/moudels/account/profile/username_manager.py
remote/moudels/admin/__init__.py
remote/moudels/admin/admin_manager.py
remote/moudels/analytics/__init__.py
remote/moudels/analytics/analytics_manager.py
remote/moudels/batch/__init__.py
remote/moudels/batch/batch_manager.py
remote/moudels/batch/batch_scheduler.py
remote/moudels/core/__init__.py
remote/moudels/core/config.py
remote/moudels/core/getcode_controller.py
remote/moudels/core/help_menu.py
remote/moudels/core/precise_engine.py
remote/moudels/core/response_manager.py
remote/moudels/core/restart_module.py
remote/moudels/db/__init__.py
remote/moudels/db/db_monitor.py
remote/moudels/db/sqlite_utils.py
remote/moudels/group/__init__.py
remote/moudels/group/join_controller.py
remote/moudels/group/joiner.py
remote/moudels/group/leave_controller.py
remote/moudels/group/lefter.py
remote/moudels/spammer/__init__.py
remote/moudels/spammer/spammer.py
remote/moudels/spammer/speed_manager.py
remote/moudels/spammer/stop_manager.py
remote/moudels/spammer/اسپمر با تاخیر اکانت به اکانت/spammer.py
remote/moudels/spammer/اسپمر با تاخیر ست به ست/spammer.py
remote/moudels/text/__init__.py
remote/moudels/text/caption_manager.py
remote/moudels/text/finaly_text.py
remote/moudels/text/mention_manager.py
remote/moudels/text/text_manager.py
remote/moudels/utils/__init__.py
xt_remote-1.9.51.dist-info/licenses/LICENSE
xt_remote-1.9.51.dist-info/METADATA
xt_remote-1.9.51.dist-info/WHEEL
xt_remote-1.9.51.dist-info/top_level.txt
xt_remote-1.9.51.dist-info/RECORD
