Metadata-Version: 2.4
Name: XT_Remote
Version: 1.9.51
Summary: Remote client framework for Telegram automation using Pyrogram
Home-page: https://github.com/MohammadAhmadi-R/XT_Remote
Author: MrAhmadiRad
Author-email: MohammadAhmadiRad <mohammadahmadirad69@gmail.com>
License: MIT
Project-URL: Homepage, https://github.com/MohammadAhmadi-R/XT_Remote
Classifier: Programming Language :: Python :: 3
Classifier: Programming Language :: Python :: 3.8
Classifier: Programming Language :: Python :: 3.9
Classifier: Programming Language :: Python :: 3.10
Classifier: Programming Language :: Python :: 3.11
Classifier: Programming Language :: Python :: 3.12
Classifier: License :: OSI Approved :: MIT License
Classifier: Operating System :: OS Independent
Classifier: Framework :: AsyncIO
Requires-Python: >=3.8
License-File: LICENSE
Requires-Dist: pyrogram>=2.0.106
Requires-Dist: httpx>=0.27.0
Requires-Dist: pytz>=2023.3
Dynamic: author
Dynamic: home-page
Dynamic: license-file
Dynamic: requires-python
